ordeq_spark/__init__.py
ordeq_spark/_version.py
ordeq_spark/py.typed
ordeq_spark/utils.py
ordeq_spark/hooks/__init__.py
ordeq_spark/hooks/spark_explain.py
ordeq_spark/hooks/spark_job_group.py
ordeq_spark/io/__init__.py
ordeq_spark/io/dataframe.py
ordeq_spark/io/jdbc.py
ordeq_spark/io/session.py
ordeq_spark/io/types.py
ordeq_spark/io/files/__init__.py
ordeq_spark/io/files/csv.py
ordeq_spark/io/files/json.py
ordeq_spark/io/files/parquet.py
ordeq_spark/io/tables/__init__.py
ordeq_spark/io/tables/global_temp_view.py
ordeq_spark/io/tables/hive.py
ordeq_spark/io/tables/iceberg.py
ordeq_spark/io/tables/table.py
ordeq_spark/io/tables/temp_view.py
ordeq_spark-2.2.0.dist-info/licenses/LICENSE
ordeq_spark-2.2.0.dist-info/METADATA
ordeq_spark-2.2.0.dist-info/WHEEL
ordeq_spark-2.2.0.dist-info/top_level.txt
ordeq_spark-2.2.0.dist-info/RECORD
