Metadata-Version: 2.4
Name: ordeq_spark
Version: 2.2.0
Summary: Apache Spark integration for Ordeq
Author: Niels Neerhoff, Simon Brugman
Maintainer: Niels Neerhoff, Simon Brugman
License-Expression: MIT
Requires-Python: >=3.10
License-File: LICENSE
Requires-Dist: ordeq>=1.4.0
Requires-Dist: pyspark>=3.3.1
Dynamic: license-file
